django_llm_poison/__init__.py
django_llm_poison/admin.py
django_llm_poison/agents.py
django_llm_poison/apps.py
django_llm_poison/markov.py
django_llm_poison/models.py
django_llm_poison/migrations/0001_initial.py
django_llm_poison/migrations/__init__.py
django_llm_poison/templatetags/poison.py
django_llm_poison-0.2.2.dist-info/METADATA
django_llm_poison-0.2.2.dist-info/WHEEL
django_llm_poison-0.2.2.dist-info/entry_points.txt
django_llm_poison-0.2.2.dist-info/licenses/LICENSE
django_llm_poison-0.2.2.dist-info/RECORD
