Metadata-Version: 2.4
Name: django-llm-poison
Version: 0.2.2
Summary: Serves markov chains to LLM bots.
Author-email: Austin Riba <austin@m51.io>
License-File: LICENSE
Requires-Python: >=3.13.1
Requires-Dist: markovify>=0.9.4
